README.md
setup.py
hypothesis_ethereum/__init__.py
hypothesis_ethereum/builder.py
hypothesis_ethereum.egg-info/PKG-INFO
hypothesis_ethereum.egg-info/SOURCES.txt
hypothesis_ethereum.egg-info/dependency_links.txt
hypothesis_ethereum.egg-info/not-zip-safe
hypothesis_ethereum.egg-info/requires.txt
hypothesis_ethereum.egg-info/top_level.txt